MANIFEST.in
README.txt
setup.py
docs/HISTORY.txt
docs/LICENSE.txt
src/infrae/__init__.py
src/infrae.rest.egg-info/PKG-INFO
src/infrae.rest.egg-info/SOURCES.txt
src/infrae.rest.egg-info/dependency_links.txt
src/infrae.rest.egg-info/namespace_packages.txt
src/infrae.rest.egg-info/not-zip-safe
src/infrae.rest.egg-info/requires.txt
src/infrae.rest.egg-info/top_level.txt
src/infrae/rest/__init__.py
src/infrae/rest/components.py
src/infrae/rest/configure.zcml
src/infrae/rest/ftesting.zcml
src/infrae/rest/interfaces.py
src/infrae/rest/meta.py
src/infrae/rest/tests/__init__.py
src/infrae/rest/tests/test_grok.py
src/infrae/rest/tests/grok/__init__.py
src/infrae/rest/tests/grok/absoluteurl.py
src/infrae/rest/tests/grok/json.py
src/infrae/rest/tests/grok/nested.py
src/infrae/rest/tests/grok/noexisting.txt
src/infrae/rest/tests/grok/require.py
src/infrae/rest/tests/grok/simple.py
src/infrae/rest/tests/grok/template.py
src/infrae/rest/tests/grok/template_fixture/__init__.py
src/infrae/rest/tests/grok/template_fixture/template.py
src/infrae/rest/tests/grok/template_fixture/static/style.css
src/infrae/rest/tests/grok/template_fixture/template_templates/formtemplate.pt