Metadata-Version: 1.0
Name: infrae.rest
Version: 1.3
Summary: Define a REST API to access and manage Zope 2 content
Home-page: http://infrae.com/products/silva
Author: Infrae
Author-email: info@infrae.com
License: BSD
Keywords: silva cms rest api zope
Platform: UNKNOWN
Classifier: Framework :: Zope2
Classifier: License :: OSI Approved :: BSD License
Classifier: Programming Language :: Python
Classifier: Topic :: Software Development :: Libraries :: Python Modules
